leetscrape_updated/__init__.py
leetscrape_updated/_constants.py
leetscrape_updated/_helper.py
leetscrape_updated/extract_solution.py
leetscrape_updated/generate_code_stub.py
leetscrape_updated/models.py
leetscrape_updated/question.py
leetscrape_updated/questions_list.py
leetscrape_updated/scripts.py
leetscrape_updated/utils.py
leetscrape_updated-0.0.1.dist-info/LICENSE
leetscrape_updated-0.0.1.dist-info/METADATA
leetscrape_updated-0.0.1.dist-info/WHEEL
leetscrape_updated-0.0.1.dist-info/entry_points.txt
leetscrape_updated-0.0.1.dist-info/RECORD
