Metadata-Version: 2.3
Name: leetscrape_updated
Version: 0.0.1
Summary: Fork of Leetscrape with resolved pandas issues and bumped pydantic
License: MIT
Author: Maxat Nukhayev
Author-email: maxat.nukhayev@gmail.com
Requires-Python: >=3.10,<4.0
Classifier: License :: OSI Approved :: MIT License
Classifier: Programming Language :: Python :: 3
Classifier: Programming Language :: Python :: 3.10
Classifier: Programming Language :: Python :: 3.11
Classifier: Programming Language :: Python :: 3.12
Classifier: Programming Language :: Python :: 3.13
Requires-Dist: black (>=22.12.0,<23.0.0)
Requires-Dist: docstring-parser (>=0.15,<0.16)
Requires-Dist: markdownify (>=0.11.6,<0.12.0)
Requires-Dist: marko (>=1.2.2,<2.0.0)
Requires-Dist: numpy (==1.24.4)
Requires-Dist: pandas (==1.5.3)
Requires-Dist: pydantic (>=2.0.0,<3.0.0)
Requires-Dist: requests (>=2.28.2,<3.0.0)
Requires-Dist: tqdm (>=4.64.1,<5.0.0)
Project-URL: Documentation, https://leetscrape.nikhilravi.com/
Project-URL: Repository, https://github.com/shneeki/LeetScrape
